tuxpkg/__init__.py
tuxpkg/__main__.py
tuxpkg/actions.py
tuxpkg/data/check-repository-key
tuxpkg/data/create-repository
tuxpkg/data/debianrules.mk
tuxpkg/data/init.sh
tuxpkg/data/release
tuxpkg/data/tuxpkg.mk
tuxpkg/data/init/.gitignore
tuxpkg/data/init/.gitlab-ci.yml.jinja2
tuxpkg/data/init/Dockerfile.ci-archlinux
tuxpkg/data/init/Dockerfile.ci-debian
tuxpkg/data/init/Dockerfile.ci-fedora
tuxpkg/data/init/Makefile.jinja2
tuxpkg/data/init/README.md.jinja2
tuxpkg/data/init/{{project}}.PKGBUILD.jinja2
tuxpkg/data/init/{{project}}.spec.jinja2
tuxpkg/data/init/.github/workflows/ci.yml.jinja2
tuxpkg/data/init/debian/changelog.jinja2
tuxpkg/data/init/debian/control.jinja2
tuxpkg/data/init/debian/gbp.conf
tuxpkg/data/init/debian/rules.jinja2
tuxpkg/data/init/debian/source/format
tuxpkg/data/init/test/__init__.py
tuxpkg/data/init/test/test_{{module}}.py.jinja2
tuxpkg/data/init/{{module}}/__init__.py.jinja2
tuxpkg-0.19.0.dist-info/entry_points.txt
tuxpkg-0.19.0.dist-info/licenses/LICENSE
tuxpkg-0.19.0.dist-info/WHEEL
tuxpkg-0.19.0.dist-info/METADATA
tuxpkg-0.19.0.dist-info/RECORD
