Metadata-Version: 2.4
Name: tuxpkg
Version: 0.19.0
Summary: Release automation tool for Python projects
Home-page: https://gitlab.com/Linaro/tuxpkg
Author: Antonio Terceiro
Author-email: antonio.terceiro@linaro.org
Maintainer: Anders Roxell, Ben Copeland
Maintainer-email: anders.roxell@linaro.org, ben.copeland@linaro.org
Classifier: License :: OSI Approved :: MIT License
License-File: LICENSE
Requires-Dist: jinja2
